opengrokfs/__init__.py
opengrokfs/cscope.py
opengrokfs/grep.py
opengrokfs/opengrok.py
opengrokfs/opengrokfs.py
opengrokfs-0.2.1.dist-info/DESCRIPTION.rst
opengrokfs-0.2.1.dist-info/METADATA
opengrokfs-0.2.1.dist-info/RECORD
opengrokfs-0.2.1.dist-info/WHEEL
opengrokfs-0.2.1.dist-info/entry_points.txt
opengrokfs-0.2.1.dist-info/metadata.json
opengrokfs-0.2.1.dist-info/top_level.txt
