Metadata-Version: 2.0
Name: opengrokfs
Version: 0.2.1
Summary: OpenGrok FUSE filesystem and tools
Home-page: https://github.com/rabinv/opengrokfs
Author: Rabin Vincent
Author-email: rabin@rab.in
License: MIT
Platform: UNKNOWN
Classifier: Environment :: Console
Classifier: Intended Audience :: Developers
Classifier: License :: OSI Approved :: MIT License
Classifier: Programming Language :: Python
Classifier: Topic :: Software Development
Requires-Dist: attrs (>=16.3.0)
Requires-Dist: dateparser (>=0.6.0)
Requires-Dist: fusepy (>=2.0.4)
Requires-Dist: lxml (>=3.7.1)
Requires-Dist: requests (>=2.12.4)
Requires-Dist: requests-cache (>=0.4.13)
